{
  "name": "Matterbridge",
  "slug": "matterbridge",
  "categories": [17],
  "date_created": "2024-06-12",
  "type": "ct",
  "updateable": true,
  "privileged": false,
  "interface_port": 8283,
  "documentation": "https://github.com/Luligu/matterbridge/blob/main/README.md",
  "website": "https://github.com/Luligu/matterbridge",
  "logo": "https://cdn.jsdelivr.net/gh/selfhst/icons@main/webp/matterbridge.webp",
  "config_path": "",
  "description": "Matterbridge allows you to have all your Matter devices up and running in a couple of minutes without having to deal with the pairing process of each single device.",
  "description_zh": "Matterbridge 讓您可以在幾分鐘內啟動並執行所有 Matter 設備，無需處理各個設備的配對流程。",
  "description_ja": "Matterbridge により、各デバイスのペアリングプロセスに対処することなく、すべての Matter デバイスを数分で起動・実行できます。",
  "install_methods": [
    {
      "type": "default",
      "script": "ct/matterbridge.sh",
      "resources": {
        "cpu": 1,
        "ram": 1024,
        "hdd": 4,
        "os": "debian",
        "version": "13"
      }
    }
  ],
  "default_credentials": {
    "username": null,
    "password": null
  },
  "notes": [
    {
      "text": "If the LXC is created Privileged, the script will automatically set up USB passthrough.",
      "type": "warning"
    },
    {
      "text": "Updatable via the Matterbridge WebUI",
      "type": "info"
    }
  ],
  "notes_zh": [
    {
      "text": "如果 LXC 以特權模式創建，指令碼將自動設置 USB 直通。",
      "type": "warning"
    },
    {
      "text": "可透過 Matterbridge 網頁介面更新",
      "type": "info"
    }
  ],
  "notes_ja": [
    {
      "text": "LXC が特権で作成されている場合、スクリプトは自動的に USB パススルーをセットアップします。",
      "type": "warning"
    },
    {
      "text": "Matterbridge WebUI から更新可能",
      "type": "info"
    }
  ]
}
