{
  "name": "Redlib",
  "slug": "alpine-redlib",
  "categories": [10],
  "date_created": "2025-08-25",
  "type": "ct",
  "updateable": true,
  "privileged": false,
  "interface_port": 5252,
  "documentation": "https://github.com/redlib-org/redlib/blob/main/README.md",
  "website": "https://github.com/redlib-org/redlib",
  "logo": "https://cdn.jsdelivr.net/gh/selfhst/icons@main/webp/redlib.webp",
  "config_path": "/opt/redlib/redlib.conf",
  "description": "An alternative private front-end to Reddit. Redlib hopes to provide an easier way to browse Reddit, without the ads, trackers, and bloat.",
  "description_zh": "Reddit 的替代私人前端。Redlib 希望提供一種更簡單的方式來瀏覽 Reddit，而無需廣告、追蹤器和臃腫。",
  "description_ja": "Redditの代替プライベートフロントエンド。Redlibは、広告、トラッカー、ブロートなしでRedditをブラウズするより簡単な方法を提供することを目指しています。",
  "install_methods": [
    {
      "type": "default",
      "script": "ct/alpine-redlib.sh",
      "resources": {
        "cpu": 1,
        "ram": 512,
        "hdd": 1,
        "os": "alpine",
        "version": "3.23"
      }
    }
  ],
  "default_credentials": {
    "username": null,
    "password": null
  },
  "notes": []
}
